Projeto-3/detector/results_detector_TB/design.sv
module d_ff(d, clk, q, q_bar); 
  input d, clk;
  output reg q, q_bar;

  always @(posedge clk) begin
    q <= d;
    q_bar <= !d;
  end
endmodule

// ESTRUTURAL
module detector_estrutural(x, clk, y);
  input x, clk;
  output y;
  wire a1, a2, b1, b2, c1, c1_bar, c2, c2_bar;

  d_ff ff1(b1, clk, c1, c1_bar);
  d_ff ff2(b2, clk, c2, c2_bar);

  or(a1, c1, c2);
  or(a2, c1, c2_bar);

  and(b1, x, a1);
  and(b2, x, a2);

  and(y, x, c1, c2);
endmodule


// DATAFLOW
module detector_dataflow(x, clk, y);
  input x, clk;
  output reg y;
  reg d0, d1;

  assign y = d0 & d1 & x;

  always @(posedge clk) begin
    d0 <= x & (d1 | ~d0);
    d1 <= x & (d1 | d0);
  end
endmodule


// COMPORTAMENTAL
module detector_comportamental(x, clk, y);
  input x, clk;
  output reg y;

  parameter S0 = 2'b00;
  parameter S1 = 2'b01;
  parameter S2 = 2'b10;
  parameter S3 = 2'b11;

  reg[1:0] estado_atual, estado_futuro;

  assign y = (estado_atual == S3 ? 1 : 0);

  always @(posedge clk) begin
    if (x == 0) begin
      estado_atual <= S0;
    end
    else begin
      estado_atual <= estado_futuro;
    end
  end

  always @(estado_atual or x) begin
    case (estado_atual)
      S0: begin
        if (x == 1)
          estado_futuro <= S1;
      end
      S1: begin
        if (x == 1)
          estado_futuro <= S2;
      end
      S2: begin
        if (x == 1)
          estado_futuro <= S3;
      end
      S3: begin
        // Se a entrada continuar sendo 1 continuará no estado S3
        if (x == 1)
          estado_futuro <= S3;
      end
    endcase
  end
endmodule

Projeto-3/detector/results_detector_TB/testbench.sv
`timescale 1ns/10ps 

module detector_tb;
  reg x, clk;
  wire y;
  wire out1, out2, out3;

  // DUT - Estrutural
  detector_estrutural DUT1 (
    .x(x),
    .clk(clk),
    .y(out1)
  );

  // DUT - Dataflow
  detector_dataflow DUT2 (
    .x(x),
    .clk(clk), 
    .y(out2)
  );

  // DUT - Comportamental
  detector_comportamental DUT3 (
    .x(x),
    .clk(clk), 
    .y(out3)
  );

  initial begin
    $dumpfile("dump.vcd");
    $dumpvars;
    #10000 $finish;
  end

  // Inputs para teste
  initial begin
    clk = 0;
    x = 0;
    display_outputs;

    toggle_clk;
    display_outputs;
    
    x = 1;
    toggle_clk;
    display_outputs;

    toggle_clk;
    display_outputs;

    // A saída deve ser 1 (Mealy)
    toggle_clk;
    display_outputs;
    
    x = 0;
    toggle_clk;
    display_outputs;

    x = 1;
    toggle_clk;
    display_outputs;

    toggle_clk;
    display_outputs;

    // A saída deve ser 1 (Mealy)
    toggle_clk;
    display_outputs;

    // A saída deve ser 1
    toggle_clk;
    display_outputs;

    // A saída deve ser 1
    toggle_clk;
    display_outputs;

    x = 0;
    toggle_clk;
    display_outputs;
  end
  
  task toggle_clk;
    begin
      #10 clk = ~clk;
      #10 clk = ~clk;
    end
  endtask

  task display_outputs;
    begin
      $display("Estrutural: %b, Dataflow: %b, Comportamental: %b", out1, out2, out3);
    end
  endtask

endmodule

Projeto-3/detector/results_detector_TB/dump.vcd
$date
Tue May 24 17:20:00 2022
$end
$version
Riviera-PRO Version 2020.04.130.7729
$end
$timescale
10 ps
$end

$scope module detector_tb $end
$var wire 1 ! y $end
$var wire 1 " out1 $end
$var wire 1 # out2 $end
$var wire 1 $ out3 $end
$var reg 1 % x $end
$var reg 1 & clk $end

$scope module DUT1 $end
$var wire 1 ' x $end
$var wire 1 ( clk $end
$var wire 1 " y $end
$var wire 1 ) a1 $end
$var wire 1 * a2 $end
$var wire 1 + b1 $end
$var wire 1 , b2 $end
$var wire 1 - c1 $end
$var wire 1 . c1_bar $end
$var wire 1 / c2 $end
$var wire 1 0 c2_bar $end

$scope module ff1 $end
$var wire 1 + d $end
$var wire 1 ( clk $end
$var reg 1 1 q $end
$var reg 1 2 q_bar $end
$upscope $end


$scope module ff2 $end
$var wire 1 , d $end
$var wire 1 ( clk $end
$var reg 1 3 q $end
$var reg 1 4 q_bar $end
$upscope $end

$upscope $end


$scope module DUT2 $end
$var wire 1 ' x $end
$var wire 1 ( clk $end
$var reg 1 5 y $end
$var reg 1 6 d0 $end
$var reg 1 7 d1 $end
$upscope $end


$scope module DUT3 $end
$var wire 1 ' x $end
$var wire 1 ( clk $end
$var reg 1 8 y $end
$var reg 2 9 estado_atual [1:0] $end
$var reg 2 : estado_futuro [1:0] $end
$var parameter 2 ; S0 [1:0] $end
$var parameter 2 < S1 [1:0] $end
$var parameter 2 = S2 [1:0] $end
$var parameter 2 > S3 [1:0] $end
$upscope $end


$scope task toggle_clk $end
$upscope $end


$scope task display_outputs $end
$upscope $end

$upscope $end

$enddefinitions $end
$dumpvars
z!
0"
0#
x$
0%
0&
0'
0(
x)
x*
0+
0,
x-
x.
x/
x0
x1
x2
x3
x4
05
x6
x7
x8
bx 9
bx :
b0 ;
b1 <
b10 =
b11 >
$end
#1000
1&
1(
01
12
03
14
06
07
b0 9
08
0$
10
0/
1.
0-
0)
1*
#2000
0&
1%
1'
0(
1,
b1 :
#3000
1&
1(
13
04
16
b1 9
00
1/
1)
0*
0,
1+
b10 :
#4000
0&
0(
#5000
1&
1(
11
02
03
14
06
17
b10 9
10
0/
0.
1-
1*
1,
b11 :
#6000
0&
0(
#7000
1&
1(
13
04
16
b11 9
15
18
1$
1#
00
1/
1"
#8000
0&
0%
0'
05
0(
0#
0"
0,
0+
#9000
1&
1(
01
12
03
14
06
07
b0 9
08
0$
10
0/
1.
0-
0)
#10000
0&
1%
1'
0(
1,
b1 :
#11000
1&
1(
13
04
16
b1 9
00
1/
1)
0*
0,
1+
b10 :
#12000
0&
0(
#13000
1&
1(
11
02
03
14
06
17
b10 9
10
0/
0.
1-
1*
1,
b11 :
#14000
0&
0(
#15000
1&
1(
13
04
16
b11 9
15
18
1$
1#
00
1/
1"
#16000
0&
0(
#17000
1&
1(
#18000
0&
0(
#19000
1&
1(
#20000
0&
0%
0'
05
0(
0#
0"
0,
0+
#21000
1&
1(
01
12
03
14
06
07
b0 9
08
0$
10
0/
1.
0-
0)
