Projeto-4/controlador/modelsim/bomba_2.v
module bomba_2(alarme_b1, s1, s3, s4, clk, m2, alarme);
  input alarme_b1, s1, s3, s4, clk;
  output reg m2, alarme;

  parameter VAZIO = 2'b00;
  parameter ENCHENDO = 2'b01;
  parameter CHEIO = 2'b10;
  parameter ESVAZIANDO = 2'b11;

  reg[1:0] estado_atual, estado_futuro;

  always @(posedge clk) begin
    if (s3 == 0 & s4 == 0)
      estado_atual <= VAZIO;
    else if (s3 == 0 & s4 == 1)
      estado_atual <= ESVAZIANDO;
    else if (s3 == 1 & s4 == 0)
      estado_atual <= ENCHENDO;
    else if (s3 == 1 & s4 == 1)
      estado_atual <= CHEIO;
    else
      estado_atual <= estado_futuro;
  end

  always @(estado_atual or s1 or s3 or s4 or alarme_b1) begin
    estado_futuro = VAZIO;
    m2 = 0;
    alarme = 0;

    // Combinação impossível dos sensores da b1 ou tanque inferior abaixo de s1: desligar motor
    if (alarme_b1 | !s1)
      m2 <= 0;
    
    else begin
      case (estado_atual)
        VAZIO: begin
          // Mudar estado
          if (s3 == 1 & s4 == 0) begin
            estado_futuro <= ENCHENDO;
            m2 <= 1;
          end
          // Caso impossível: desligar motor e emitir alarme
          else if (
            (s3 == 0 & s4 == 1) | 
            (s3 == 1 & s4 == 1)
          ) begin
            estado_futuro <= VAZIO;
            m2 <= 0;
            alarme <= 1;
          end
          else if (s3 == 0 & s4 == 0) begin
            estado_futuro <= VAZIO;
            m2 <= 1;
          end
        end
        ENCHENDO: begin
          // Mudar estado
          if (s3 == 1 & s4 == 1) begin
            estado_futuro <= CHEIO;
            m2 <= 0;
          end
          // Caso impossível: desligar motor e emitir alarme
          else if (
            (s3 == 0 & s4 == 0) | 
            (s3 == 0 & s4 == 1)
          ) begin
            estado_futuro <= ENCHENDO;
            m2 <= 0;
            alarme <= 1;
          end
          else if (s3 == 1 & s4 == 0) begin
            estado_futuro <= ENCHENDO;
            m2 <= 1;
          end
        end
        CHEIO: begin
          // Mudar estado
          if (s3 == 1 & s4 == 0) begin
            estado_futuro <= ESVAZIANDO;
            m2 <= 0;
          end
          // Caso impossível: desligar motor e emitir alarme
          else if (
            (s3 == 0 & s4 == 0) | 
            (s3 == 0 & s4 == 1)
          ) begin
            estado_futuro <= CHEIO;
            m2 <= 0;
            alarme <= 1;
          end
          else if (s3 == 1 & s4 == 1) begin
            estado_futuro <= CHEIO;
            m2 <= 0;
          end
        end
        ESVAZIANDO: begin
          // Mudar estado
          if (s3 == 0 & s4 == 0) begin
            estado_futuro <= VAZIO;
            m2 <= 0;
          end
          // Caso impossível: desligar motor e emitir alarme
          else if (
            (s3 == 0 & s4 == 1) | 
            (s3 == 1 & s4 == 1)
          ) begin
            estado_futuro <= ESVAZIANDO;
            m2 <= 0;
            alarme <= 1;
          end
          else if (s3 == 1 & s4 == 0) begin
            estado_futuro <= ESVAZIANDO;
            m2 <= 0;
          end
        end
      endcase
    end
  end
endmodule

Projeto-4/controlador/modelsim/bomba_1.v
module bomba_1(alarme_b2, s1, s2, clk, m1, alarme);
  input alarme_b2, s1, s2, clk;
  output reg m1, alarme;

  parameter VAZIO = 2'b00;
  parameter ENCHENDO = 2'b01;
  parameter CHEIO = 2'b10;
  parameter ESVAZIANDO = 2'b11;

  reg[1:0] estado_atual, estado_futuro;

  always @(posedge clk) begin
    if (s1 == 0 & s2 == 0)
      estado_atual <= VAZIO;
    else if (s1 == 0 & s2 == 1)
      estado_atual <= ESVAZIANDO;
    else if (s1 == 1 & s2 == 0)
      estado_atual <= ENCHENDO;
    else if (s1 == 1 & s2 == 1)
      estado_atual <= CHEIO;
    else
      estado_atual <= estado_futuro;
  end

  always @(estado_atual or s1 or s2 or alarme_b2) begin
    estado_futuro = VAZIO;
    m1 = 0;
    alarme = 0;

    // Combinação impossível dos sensores da b2: desligar motor
    if (alarme_b2)
      m1 <= 0;
    
    else begin
      case (estado_atual)
        VAZIO: begin
          // Mudar estado
          if (s1 == 1 & s2 == 0) begin
            estado_futuro <= ENCHENDO;
            m1 <= 1;
          end
          // Caso impossível: desligar motor e emitir alarme
          else if (
            (s1 == 0 & s2 == 1) | 
            (s1 == 1 & s2 == 1)
          ) begin
            estado_futuro <= VAZIO;
            m1 <= 0;
            alarme <= 1;
          end
          else if (s1 == 0 & s2 == 0) begin
            estado_futuro <= VAZIO;
            m1 <= 1;
          end
        end
        ENCHENDO: begin
          // Mudar estado
          if (s1 == 1 & s2 == 1) begin
            estado_futuro <= CHEIO;
            m1 <= 0;
          end
          // Caso impossível: desligar motor e emitir alarme
          else if (
            (s1 == 0 & s2 == 0) | 
            (s1 == 0 & s2 == 1)
          ) begin
            estado_futuro <= ENCHENDO;
            m1 <= 0;
            alarme <= 1;
          end
          else if (s1 == 1 & s2 == 0) begin
            estado_futuro <= ENCHENDO;
            m1 <= 1;
          end
        end
        CHEIO: begin
          // Mudar estado
          if (s1 == 1 & s2 == 0) begin
            estado_futuro <= ESVAZIANDO;
            m1 <= 0;
          end
          // Caso impossível: desligar motor e emitir alarme
          else if (
            (s1 == 0 & s2 == 0) | 
            (s1 == 0 & s2 == 1)
          ) begin
            estado_futuro <= CHEIO;
            m1 <= 0;
            alarme <= 1;
          end
          else if (s1 == 1 & s2 == 1) begin
            estado_futuro <= CHEIO;
            m1 <= 0;
          end
        end
        ESVAZIANDO: begin
          // Mudar estado
          if (s1 == 0 & s2 == 0) begin
            estado_futuro <= VAZIO;
            m1 <= 0;
          end
          // Caso impossível: desligar motor e emitir alarme
          else if (
            (s1 == 0 & s2 == 1) | 
            (s1 == 1 & s2 == 1)
          ) begin
            estado_futuro <= ESVAZIANDO;
            m1 <= 0;
            alarme <= 1;
          end
          else if (s1 == 1 & s2 == 0) begin
            estado_futuro <= ESVAZIANDO;
            m1 <= 0;
          end
        end
      endcase
    end
  end
endmodule

Projeto-4/controlador/controlador_bombas.v
module controlador_bombas(s1, s2, s3, s4, clk, m1, m2);
  input s1, s2, s3, s4, clk;
  output m1, m2;
  wire alarme_b1, alarme_b2;

  bomba_1 B1 (alarme_b2, s1, s2, clk, m1, alarme_b1);
  bomba_2 B2 (alarme_b1 ,s1, s3, s4, clk, m2, alarme_b2);
endmodule

Projeto-4/controlador/modelsim/controlador_TB.v
`timescale 1ns/10ps 

module controlador_TB;
  reg s1, s2, s3, s4, clk;
  wire m1, m2;

  // DUT - Controlador Bombas
  controlador_bombas DUT (
    .s1(s1),
    .s2(s2),
    .s3(s3),
    .s4(s4),
    .clk(clk),
    .m1(m1),
    .m2(m2)
  );

  initial begin
    $dumpfile("dump.vcd");
    $dumpvars;
    #10000 $finish;
  end

  // Inputs para teste
  initial begin
    // Todos sinais em 0
    s1 = 0;
    s2 = 0;
    s3 = 0;
    s4 = 0;
    clk = 0;
    display_outputs;

    // TANQUE INFERIOR VAZIO
    // Acionado o clock, m1 deve ir para 1
    toggle_clk;
    display_outputs;

    // CASO IMPOSSÍVEL (TANQUE VAZIO)
    // Acionando s2 com s1 em 0, m1 e m2 devem ir para 0
    s2 = 1;
    toggle_clk;
    display_outputs;

    // TANQUE INFERIOR ENCHENDO
    // Acionando s1, m1 e m2 devem ir para 1
    s2 = 0;
    s1 = 1;
    toggle_clk;
    display_outputs;

    // TANQUE INFERIOR CHEIO
    // Acionando s2, m1 deve ir para 0, m2 deve permanecer em 1
    s2 = 1;
    toggle_clk;
    display_outputs;

    // TANQUE SUPERIOR ENCHENDO
    // Acionando s3, m2 deve permanecer em 1
    s3 = 1;
    toggle_clk;
    display_outputs;

    // CASO IMPOSSÍVEL (TANQUE ENCHENDO)
    // Acionando s4 com s3 em 0, m1 e m2 devem ir para 0
    s3 = 0;
    s4 = 1;
    toggle_clk;
    display_outputs;
    
    // TANQUE SUPERIOR CHEIO
    // Acionando s4, m2 deve ir para 0
    s3 = 1;
    s4 = 1;
    toggle_clk;
    display_outputs;

    // TANQUE INFERIOR ESVAZIANDO
    // s2 indo para 0, m1 deve ser acionado
    s2 = 0;
    toggle_clk;
    display_outputs;

    // TANQUE SUPERIOR ESVAZIANDO
    // s4 indo para 0, m2 deve ser acionado
    s4 = 0;
    toggle_clk;
    display_outputs;

    // TANQUE INFERIOR VAZIO
    // s1 indo para 0, m2 deve ir para 0
    s1 = 0;
    toggle_clk;
    display_outputs;

    // TANQUE INFERIOR E SUPERIOR ENCHENDO
    // m1 e m2 devem ir para 1
    s1 = 1;
    s2 = 0;
    s3 = 1;
    s4 = 0;
    toggle_clk;
    display_outputs;

    // TESTAR CASOS IMPOSSÍVEIS
    // m1 e m2 devem ir para 0
    s1 = 0;
    s2 = 1;
    toggle_clk;
    display_outputs;
    s1 = 1;
    s2 = 0;
    s3 = 0;
    s4 = 1;
    toggle_clk;
    display_outputs;
  end
  
  task toggle_clk;
    begin
      #10 clk = ~clk;
      #10 clk = ~clk;
    end
  endtask

  task display_outputs;
    begin
      $display(
        "s1: %b, s2: %b, s3: %b, s4: %b, Motor 1: %b, Motor 2: %b"
        , s1, s2, s3, s4, m1, m2
      );
    end
  endtask

endmodule

Projeto-4/controlador/modelsim/dump.vcd
$date
	Tue Jun 21 17:52:45 2022
$end
$version
	ModelSim Version 2020.1
$end
$timescale
	10ps
$end

$scope module controlador_TB $end
$var reg 1 ! s1 $end
$var reg 1 " s2 $end
$var reg 1 # s3 $end
$var reg 1 $ s4 $end
$var reg 1 % clk $end
$var wire 1 & m1 $end
$var wire 1 ' m2 $end

$scope task toggle_clk $end
$upscope $end

$scope task display_outputs $end
$upscope $end

$scope module DUT $end
$var wire 1 ( s1 $end
$var wire 1 ) s2 $end
$var wire 1 * s3 $end
$var wire 1 + s4 $end
$var wire 1 , clk $end
$var wire 1 & m1 $end
$var wire 1 ' m2 $end
$var wire 1 - alarme_b1 $end
$var wire 1 . alarme_b2 $end

$scope module B1 $end
$var parameter 2 / VAZIO $end
$var parameter 2 0 ENCHENDO $end
$var parameter 2 1 CHEIO $end
$var parameter 2 2 ESVAZIANDO $end
$var wire 1 . alarme_b2 $end
$var wire 1 ( s1 $end
$var wire 1 ) s2 $end
$var wire 1 , clk $end
$var reg 1 3 m1 $end
$var reg 1 4 alarme $end
$var reg 2 5 estado_atual [1:0] $end
$var reg 2 6 estado_futuro [1:0] $end
$upscope $end

$scope module B2 $end
$var parameter 2 7 VAZIO $end
$var parameter 2 8 ENCHENDO $end
$var parameter 2 9 CHEIO $end
$var parameter 2 : ESVAZIANDO $end
$var wire 1 - alarme_b1 $end
$var wire 1 ( s1 $end
$var wire 1 * s3 $end
$var wire 1 + s4 $end
$var wire 1 , clk $end
$var reg 1 ; m2 $end
$var reg 1 < alarme $end
$var reg 2 = estado_atual [1:0] $end
$var reg 2 > estado_futuro [1:0] $end
$upscope $end
$upscope $end
$upscope $end
$enddefinitions $end
#0
$dumpvars
0!
0"
0#
0$
0%
03
04
bx 5
b0 6
0;
0<
bx =
b0 >
b0 /
b1 0
b10 1
b11 2
b0 7
b1 8
b10 9
b11 :
0&
0'
0-
0.
0,
0+
0*
0)
0(
$end
#1000
1%
1,
b0 5
b0 =
13
1&
#2000
0%
1"
0,
1)
03
0&
14
1-
#3000
1%
1,
b11 5
04
0-
b11 6
14
1-
#4000
0%
0"
1!
0,
0)
1(
b0 6
04
0-
b11 6
1;
1'
#5000
1%
1,
b1 5
b0 6
b1 6
13
1&
#6000
0%
1"
0,
1)
b0 6
03
0&
b10 6
#7000
1%
1,
b10 5
b0 6
b10 6
#8000
0%
1#
0,
1*
0;
0'
b1 >
1;
1'
#9000
1%
1,
b1 =
b0 >
0;
0'
b1 >
1;
1'
#10000
0%
0#
1$
0,
0*
1+
b0 >
0;
0'
b1 >
1<
1.
b0 6
#11000
1%
1,
b11 =
b0 >
0<
0.
b11 >
1<
b10 6
1.
b0 6
#12000
0%
1#
0,
1*
b0 >
0<
0.
b11 >
1<
b10 6
1.
b0 6
#13000
1%
1,
b10 =
b0 >
0<
0.
b10 >
b10 6
#14000
0%
0"
0,
0)
b0 6
b11 6
#15000
1%
1,
b1 5
b0 6
b1 6
13
1&
#16000
0%
0$
0,
0+
b0 >
b11 >
#17000
1%
1,
b1 =
b0 >
b1 >
1;
1'
#18000
0%
0!
0,
0(
b0 6
03
b0 >
0;
0&
0'
b1 6
14
1-
#19000
1%
1,
b0 5
b0 6
04
0-
13
1&
#20000
0%
1!
0,
1(
03
0&
b1 6
13
b1 >
1;
1&
1'
#21000
1%
1,
b1 5
b0 6
03
0&
b1 6
13
1&
#22000
0%
0!
1"
0,
0(
1)
b0 6
03
b0 >
0;
0&
0'
b1 6
14
1-
#23000
1%
1,
b11 5
b0 6
04
0-
b11 6
14
1-
#24000
0%
1!
0"
0#
1$
0,
1(
0)
0*
1+
b0 6
04
0-
b11 6
b1 >
1<
1.
b0 6
#25000
1%
1,
b1 5
b11 =
b0 >
0<
0.
b11 >
1<
b1 6
13
1&
1.
b0 6
03
0&
