Projeto-4/controlador/edaplayground/design.sv
module bomba_1(alarme_b2, s1, s2, clk, m1, alarme);
  input alarme_b2, s1, s2, clk;
  output reg m1, alarme;

  parameter VAZIO = 2'b00;
  parameter ENCHENDO = 2'b01;
  parameter CHEIO = 2'b10;
  parameter ESVAZIANDO = 2'b11;

  reg[1:0] estado_atual, estado_futuro;

  always @(posedge clk) begin
    if (s1 == 0 & s2 == 0)
      estado_atual <= VAZIO;
    else if (s1 == 0 & s2 == 1)
      estado_atual <= ESVAZIANDO;
    else if (s1 == 1 & s2 == 0)
      estado_atual <= ENCHENDO;
    else if (s1 == 1 & s2 == 1)
      estado_atual <= CHEIO;
    else
      estado_atual <= estado_futuro;
  end

  always @(estado_atual or s1 or s2 or alarme_b2) begin
    estado_futuro = VAZIO;
    m1 = 0;
    alarme = 0;

    // Combinação impossível dos sensores da b2: desligar motor
    if (alarme_b2)
      m1 <= 0;
    
    else begin
      case (estado_atual)
        VAZIO: begin
          // Mudar estado
          if (s1 == 1 & s2 == 0) begin
            estado_futuro <= ENCHENDO;
            m1 <= 1;
          end
          // Caso impossível: desligar motor e emitir alarme
          else if (
            (s1 == 0 & s2 == 1) | 
            (s1 == 1 & s2 == 1)
          ) begin
            estado_futuro <= VAZIO;
            m1 <= 0;
            alarme <= 1;
          end
          else if (s1 == 0 & s2 == 0) begin
            estado_futuro <= VAZIO;
            m1 <= 1;
          end
        end
        ENCHENDO: begin
          // Mudar estado
          if (s1 == 1 & s2 == 1) begin
            estado_futuro <= CHEIO;
            m1 <= 0;
          end
          // Caso impossível: desligar motor e emitir alarme
          else if (
            (s1 == 0 & s2 == 0) | 
            (s1 == 0 & s2 == 1)
          ) begin
            estado_futuro <= ENCHENDO;
            m1 <= 0;
            alarme <= 1;
          end
          else if (s1 == 1 & s2 == 0) begin
            estado_futuro <= ENCHENDO;
            m1 <= 1;
          end
        end
        CHEIO: begin
          // Mudar estado
          if (s1 == 1 & s2 == 0) begin
            estado_futuro <= ESVAZIANDO;
            m1 <= 0;
          end
          // Caso impossível: desligar motor e emitir alarme
          else if (
            (s1 == 0 & s2 == 0) | 
            (s1 == 0 & s2 == 1)
          ) begin
            estado_futuro <= CHEIO;
            m1 <= 0;
            alarme <= 1;
          end
          else if (s1 == 1 & s2 == 1) begin
            estado_futuro <= CHEIO;
            m1 <= 0;
          end
        end
        ESVAZIANDO: begin
          // Mudar estado
          if (s1 == 0 & s2 == 0) begin
            estado_futuro <= VAZIO;
            m1 <= 0;
          end
          // Caso impossível: desligar motor e emitir alarme
          else if (
            (s1 == 0 & s2 == 1) | 
            (s1 == 1 & s2 == 1)
          ) begin
            estado_futuro <= ESVAZIANDO;
            m1 <= 0;
            alarme <= 1;
          end
          else if (s1 == 1 & s2 == 0) begin
            estado_futuro <= ESVAZIANDO;
            m1 <= 0;
          end
        end
      endcase
    end
  end
endmodule

module bomba_2(alarme_b1, s1, s3, s4, clk, m2, alarme);
  input alarme_b1, s1, s3, s4, clk;
  output reg m2, alarme;

  parameter VAZIO = 2'b00;
  parameter ENCHENDO = 2'b01;
  parameter CHEIO = 2'b10;
  parameter ESVAZIANDO = 2'b11;

  reg[1:0] estado_atual, estado_futuro;

  always @(posedge clk) begin
    if (s3 == 0 & s4 == 0)
      estado_atual <= VAZIO;
    else if (s3 == 0 & s4 == 1)
      estado_atual <= ESVAZIANDO;
    else if (s3 == 1 & s4 == 0)
      estado_atual <= ENCHENDO;
    else if (s3 == 1 & s4 == 1)
      estado_atual <= CHEIO;
    else
      estado_atual <= estado_futuro;
  end

  always @(estado_atual or s1 or s3 or s4 or alarme_b1) begin
    estado_futuro = VAZIO;
    m2 = 0;
    alarme = 0;

    // Combinação impossível dos sensores da b1 ou tanque inferior abaixo de s1: desligar motor
    if (alarme_b1 | !s1)
      m2 <= 0;
    
    else begin
      case (estado_atual)
        VAZIO: begin
          // Mudar estado
          if (s3 == 1 & s4 == 0) begin
            estado_futuro <= ENCHENDO;
            m2 <= 1;
          end
          // Caso impossível: desligar motor e emitir alarme
          else if (
            (s3 == 0 & s4 == 1) | 
            (s3 == 1 & s4 == 1)
          ) begin
            estado_futuro <= VAZIO;
            m2 <= 0;
            alarme <= 1;
          end
          else if (s3 == 0 & s4 == 0) begin
            estado_futuro <= VAZIO;
            m2 <= 1;
          end
        end
        ENCHENDO: begin
          // Mudar estado
          if (s3 == 1 & s4 == 1) begin
            estado_futuro <= CHEIO;
            m2 <= 0;
          end
          // Caso impossível: desligar motor e emitir alarme
          else if (
            (s3 == 0 & s4 == 0) | 
            (s3 == 0 & s4 == 1)
          ) begin
            estado_futuro <= ENCHENDO;
            m2 <= 0;
            alarme <= 1;
          end
          else if (s3 == 1 & s4 == 0) begin
            estado_futuro <= ENCHENDO;
            m2 <= 1;
          end
        end
        CHEIO: begin
          // Mudar estado
          if (s3 == 1 & s4 == 0) begin
            estado_futuro <= ESVAZIANDO;
            m2 <= 0;
          end
          // Caso impossível: desligar motor e emitir alarme
          else if (
            (s3 == 0 & s4 == 0) | 
            (s3 == 0 & s4 == 1)
          ) begin
            estado_futuro <= CHEIO;
            m2 <= 0;
            alarme <= 1;
          end
          else if (s3 == 1 & s4 == 1) begin
            estado_futuro <= CHEIO;
            m2 <= 0;
          end
        end
        ESVAZIANDO: begin
          // Mudar estado
          if (s3 == 0 & s4 == 0) begin
            estado_futuro <= VAZIO;
            m2 <= 0;
          end
          // Caso impossível: desligar motor e emitir alarme
          else if (
            (s3 == 0 & s4 == 1) | 
            (s3 == 1 & s4 == 1)
          ) begin
            estado_futuro <= ESVAZIANDO;
            m2 <= 0;
            alarme <= 1;
          end
          else if (s3 == 1 & s4 == 0) begin
            estado_futuro <= ESVAZIANDO;
            m2 <= 0;
          end
        end
      endcase
    end
  end
endmodule

module controlador_bombas(s1, s2, s3, s4, clk, m1, m2);
  input s1, s2, s3, s4, clk;
  output m1, m2;
  wire alarme_b1, alarme_b2;

  bomba_1 B1 (alarme_b2, s1, s2, clk, m1, alarme_b1);
  bomba_2 B2 (alarme_b1 ,s1, s3, s4, clk, m2, alarme_b2);
endmodule

Projeto-4/controlador/edaplayground/testbench.sv
`timescale 1ns/10ps 

module controlador_TB;
  reg s1, s2, s3, s4, clk;
  wire m1, m2;

  // DUT - Controlador Bombas
  controlador_bombas DUT (
    .s1(s1),
    .s2(s2),
    .s3(s3),
    .s4(s4),
    .clk(clk),
    .m1(m1),
    .m2(m2)
  );

  initial begin
    $dumpfile("dump.vcd");
    $dumpvars;
    #10000 $finish;
  end

  // Inputs para teste
  initial begin
    // Todos sinais em 0
    s1 = 0;
    s2 = 0;
    s3 = 0;
    s4 = 0;
    clk = 0;
    display_outputs;

    // TANQUE INFERIOR VAZIO
    // Acionado o clock, m1 deve ir para 1
    toggle_clk;
    display_outputs;

    // CASO IMPOSSÍVEL (TANQUE VAZIO)
    // Acionando s2 com s1 em 0, m1 e m2 devem ir para 0
    s2 = 1;
    toggle_clk;
    display_outputs;

    // TANQUE INFERIOR ENCHENDO
    // Acionando s1, m1 e m2 devem ir para 1
    s2 = 0;
    s1 = 1;
    toggle_clk;
    display_outputs;

    // TANQUE INFERIOR CHEIO
    // Acionando s2, m1 deve ir para 0, m2 deve permanecer em 1
    s2 = 1;
    toggle_clk;
    display_outputs;

    // TANQUE SUPERIOR ENCHENDO
    // Acionando s3, m2 deve permanecer em 1
    s3 = 1;
    toggle_clk;
    display_outputs;

    // CASO IMPOSSÍVEL (TANQUE ENCHENDO)
    // Acionando s4 com s3 em 0, m1 e m2 devem ir para 0
    s3 = 0;
    s4 = 1;
    toggle_clk;
    display_outputs;
    
    // TANQUE SUPERIOR CHEIO
    // Acionando s4, m2 deve ir para 0
    s3 = 1;
    s4 = 1;
    toggle_clk;
    display_outputs;

    // TANQUE INFERIOR ESVAZIANDO
    // s2 indo para 0, m1 deve ser acionado
    s2 = 0;
    toggle_clk;
    display_outputs;

    // TANQUE SUPERIOR ESVAZIANDO
    // s4 indo para 0, m2 deve ser acionado
    s4 = 0;
    toggle_clk;
    display_outputs;

    // TANQUE INFERIOR VAZIO
    // s1 indo para 0, m2 deve ir para 0
    s1 = 0;
    toggle_clk;
    display_outputs;

    // TANQUE INFERIOR E SUPERIOR ENCHENDO
    // m1 e m2 devem ir para 1
    s1 = 1;
    s2 = 0;
    s3 = 1;
    s4 = 0;
    toggle_clk;
    display_outputs;

    // TESTAR CASOS IMPOSSÍVEIS
    // m1 e m2 devem ir para 0
    s1 = 0;
    s2 = 1;
    toggle_clk;
    display_outputs;
    s1 = 1;
    s2 = 0;
    s3 = 0;
    s4 = 1;
    toggle_clk;
    display_outputs;
  end
  
  task toggle_clk;
    begin
      #10 clk = ~clk;
      #10 clk = ~clk;
    end
  endtask

  task display_outputs;
    begin
      $display(
        "s1: %b, s2: %b, s3: %b, s4: %b, Motor 1: %b, Motor 2: %b"
        , s1, s2, s3, s4, m1, m2
      );
    end
  endtask

endmodule

Projeto-4/controlador/edaplayground/dump.vcd
$date
	Tue Jun 21 20:58:56 2022
$end
$version
	Icarus Verilog
$end
$timescale
	10ps
$end
$scope module controlador_TB $end
$var wire 1 ! m1 $end
$var wire 1 " m2 $end
$var reg 1 # clk $end
$var reg 1 $ s1 $end
$var reg 1 % s2 $end
$var reg 1 & s3 $end
$var reg 1 ' s4 $end
$scope module DUT $end
$var wire 1 ( alarme_b1 $end
$var wire 1 ) alarme_b2 $end
$var wire 1 * clk $end
$var wire 1 ! m1 $end
$var wire 1 " m2 $end
$var wire 1 + s1 $end
$var wire 1 , s2 $end
$var wire 1 - s3 $end
$var wire 1 . s4 $end
$scope module B1 $end
$var wire 1 ) alarme_b2 $end
$var wire 1 * clk $end
$var wire 1 + s1 $end
$var wire 1 , s2 $end
$var reg 1 / alarme $end
$var reg 2 0 estado_atual [1:0] $end
$var reg 2 1 estado_futuro [1:0] $end
$var reg 1 2 m1 $end
$upscope $end
$scope module B2 $end
$var wire 1 ( alarme_b1 $end
$var wire 1 * clk $end
$var wire 1 + s1 $end
$var wire 1 - s3 $end
$var wire 1 . s4 $end
$var reg 1 3 alarme $end
$var reg 2 4 estado_atual [1:0] $end
$var reg 2 5 estado_futuro [1:0] $end
$var reg 1 6 m2 $end
$upscope $end
$upscope $end
$scope task display_outputs $end
$upscope $end
$scope task toggle_clk $end
$upscope $end
$upscope $end
$enddefinitions $end
#0
$dumpvars
06
b0 5
bx 4
03
02
b0 1
bx 0
0/
0.
0-
0,
0+
0*
0)
0(
0'
0&
0%
0$
0#
0"
0!
$end
#1000
12
1!
b0 0
b0 4
1#
1*
#2000
1/
1(
02
0!
1%
1,
0#
0*
#3000
b11 1
1/
1(
b11 0
1#
1*
#4000
16
1"
0/
0(
b11 1
1$
1+
0%
0,
0#
0*
#5000
12
1!
b1 1
b1 0
1#
1*
#6000
02
0!
b10 1
1%
1,
0#
0*
#7000
b10 1
b10 0
1#
1*
#8000
b1 5
16
1"
1&
1-
0#
0*
#9000
16
1"
b1 5
b1 4
1#
1*
#10000
b0 1
13
1)
06
0"
b1 5
1'
1.
0&
0-
0#
0*
#11000
b0 1
13
1)
b11 5
b11 4
1#
1*
#12000
b0 1
13
1)
b11 5
1&
1-
0#
0*
#13000
b10 1
03
0)
b10 5
b10 4
1#
1*
#14000
b11 1
0%
0,
0#
0*
#15000
12
1!
b1 1
b1 0
1#
1*
#16000
b11 5
0'
0.
0#
0*
#17000
16
1"
b1 5
b1 4
1#
1*
#18000
1/
1(
06
0"
b0 5
02
0!
b1 1
0$
0+
0#
0*
#19000
12
1!
0/
0(
b0 1
b0 0
1#
1*
#20000
16
1"
b1 5
b1 1
12
1!
1$
1+
0#
0*
#21000
12
1!
b1 1
b1 0
1#
1*
#22000
1/
1(
06
0"
b0 5
02
0!
b1 1
1%
1,
0$
0+
0#
0*
#23000
1/
1(
b11 1
b11 0
1#
1*
#24000
13
1)
b1 5
0/
0(
b0 1
1'
1.
0&
0-
0%
0,
1$
1+
0#
0*
#25000
02
0!
b0 1
13
1)
b11 5
b1 0
b11 4
1#
1*
