Projeto-5/fifo/modelsim/fifo.v
module fifo(clk, reset, data_in, write, read, empty, full, data_out);
  input clk, reset;
  input [19:0] data_in;
  input write, read;
  output reg empty, full;
  output reg [19:0] data_out;

  // 20 bits de largura e 16 bits de profundidade
  reg [19:0] fifo_memory [0:15];
  reg [3:0] read_address, write_address;
  reg [3:0] count;  // contador de operações

  // Operação de escrita
  always @(posedge clk) begin
    if ((write & !full) | (write & read)) begin
      fifo_memory[write_address] <= data_in;
    end
  end

  // Operação de leitura
  always @(posedge clk) begin
    if ((read & !empty) | (read & write)) begin
      data_out <= fifo_memory[read_address];
    end
    else begin
      data_out <= 20'bz;  // alta impedância
    end
  end

  // Controlador dos endereços de escrita e leitura
  always @(posedge clk) begin
    if (reset) begin
      write_address <= 0;
      read_address <= 0;
    end
    else begin
      if ((write & !full) | (write & read)) begin
        write_address <= write_address + 4'b0001;
      end
      if ((read & !empty) | (read & write)) begin
        read_address <= read_address + 4'b0001;
      end
    end
  end

  // Controlador do contador de operações
  always @(posedge clk) begin
    if (reset) begin
      count <= 0;
    end
    else begin
      case ({write, read})
        2'b00: begin
          count <= count;
        end
        2'b01: begin
          if (count != 4'b0000)
            count <= count - 4'b0001;
        end
        2'b10: begin
          if (count != 4'b1111)
            count <= count + 4'b0001;
        end
        2'b11: begin
          count <= count;
        end
        default:
          count <= count;
      endcase
    end
  end

  // Controlador do estado vazio da memória
  always @(count) begin
    if (count == 4'b0000) begin
      empty <= 1;
    end
    else begin
      empty <= 0;
    end
  end
  // Controlador do estado cheio da memória
  always @(count) begin
    if (count == 4'b1111) begin
      full <= 1;
    end
    else begin
      full <= 0;
    end
  end
endmodule

Projeto-5/fifo/modelsim/fifo_TB.v
`timescale 1ns/10ps 

module fifo_TB;
  reg clk, reset, write, read;
  reg [19:0] data_in;
  wire empty, full;
  wire [19:0] data_out;

  // DUT - Memória FIFO
  fifo DUT (
    .clk(clk),
    .reset(reset),
    .data_in(data_in),
    .write(write),
    .read(read),
    .empty(empty),
    .full(full),
    .data_out(data_out)
  );

  initial begin
    $dumpfile("dump.vcd");
    $dumpvars;
    #10000 $finish;
  end

  // Inputs para teste
  initial begin
    // Sinais em 0 e reset em 1
    clk = 0;
    reset = 1;
    data_in = 20'b0;
    write = 0;
    read = 0;
    display_outputs;
    toggle_clk;
    // A saída (data_out) deve ser alta impedância
    display_outputs;

    // Escrevendo registros
    reset = 0;
    write = 1;
    data_in = 20'b00000000000000000001;
    toggle_clk;
    display_outputs;
    data_in = 20'b00000000000000000011;
    toggle_clk;
    display_outputs;
    data_in = 20'b00000000000000000101;
    toggle_clk;
    display_outputs;
    
    // Ativando sinal de leitura
    // A saída do FIFO não deve ser mais alta impedância
    read = 1;
    toggle_clk;
    display_outputs;
    data_in = 20'b00000000000000001101;
    toggle_clk;
    display_outputs;

    // Desativando escrita
    write = 0;
    toggle_clk;
    display_outputs;
    // Essa entrada não deve ir para saída
    data_in = 20'b00111000000000001101;
    toggle_clk;
    display_outputs;
  end
  
  task toggle_clk;
    begin
      #10 clk = ~clk;
      #10 clk = ~clk;
    end
  endtask

  task display_outputs;
    begin
      #20 $display(
        "data_in=%b, read=%b, write=%b, empty=%b ,full=%b, data_out=%b",
        data_in, read, write, empty, full, data_out
      );
    end
  endtask
endmodule

Projeto-5/fifo/modelsim/dump.vcd
$date
	Mon Jul  4 23:37:06 2022
$end
$version
	ModelSim Version 2020.1
$end
$timescale
	10ps
$end

$scope module fifo_TB $end
$var reg 1 ! clk $end
$var reg 1 " reset $end
$var reg 1 # write $end
$var reg 1 $ read $end
$var reg 20 % data_in [19:0] $end
$var wire 1 & empty $end
$var wire 1 ' full $end
$var wire 1 ( data_out [19] $end
$var wire 1 ) data_out [18] $end
$var wire 1 * data_out [17] $end
$var wire 1 + data_out [16] $end
$var wire 1 , data_out [15] $end
$var wire 1 - data_out [14] $end
$var wire 1 . data_out [13] $end
$var wire 1 / data_out [12] $end
$var wire 1 0 data_out [11] $end
$var wire 1 1 data_out [10] $end
$var wire 1 2 data_out [9] $end
$var wire 1 3 data_out [8] $end
$var wire 1 4 data_out [7] $end
$var wire 1 5 data_out [6] $end
$var wire 1 6 data_out [5] $end
$var wire 1 7 data_out [4] $end
$var wire 1 8 data_out [3] $end
$var wire 1 9 data_out [2] $end
$var wire 1 : data_out [1] $end
$var wire 1 ; data_out [0] $end

$scope task toggle_clk $end
$upscope $end

$scope task display_outputs $end
$upscope $end

$scope module DUT $end
$var wire 1 < clk $end
$var wire 1 = reset $end
$var wire 1 > data_in [19] $end
$var wire 1 ? data_in [18] $end
$var wire 1 @ data_in [17] $end
$var wire 1 A data_in [16] $end
$var wire 1 B data_in [15] $end
$var wire 1 C data_in [14] $end
$var wire 1 D data_in [13] $end
$var wire 1 E data_in [12] $end
$var wire 1 F data_in [11] $end
$var wire 1 G data_in [10] $end
$var wire 1 H data_in [9] $end
$var wire 1 I data_in [8] $end
$var wire 1 J data_in [7] $end
$var wire 1 K data_in [6] $end
$var wire 1 L data_in [5] $end
$var wire 1 M data_in [4] $end
$var wire 1 N data_in [3] $end
$var wire 1 O data_in [2] $end
$var wire 1 P data_in [1] $end
$var wire 1 Q data_in [0] $end
$var wire 1 R write $end
$var wire 1 S read $end
$var reg 1 T empty $end
$var reg 1 U full $end
$var reg 20 V data_out [19:0] $end
$var reg 4 W read_address [3:0] $end
$var reg 4 X write_address [3:0] $end
$var reg 4 Y count [3:0] $end
$upscope $end
$upscope $end
$enddefinitions $end
#0
$dumpvars
0!
1"
0#
0$
b0 %
xT
xU
bx V
bx W
bx X
bx Y
x&
x'
x;
x:
x9
x8
x7
x6
x5
x4
x3
x2
x1
x0
x/
x.
x-
x,
x+
x*
x)
x(
0S
0R
0Q
0P
0O
0N
0M
0L
0K
0J
0I
0H
0G
0F
0E
0D
0C
0B
0A
0@
0?
0>
1=
0<
$end
#3000
1!
1<
bz V
b0 X
b0 W
b0 Y
z;
z:
z9
z8
z7
z6
z5
z4
z3
z2
z1
z0
z/
z.
z-
z,
z+
z*
z)
z(
1T
0U
1&
0'
#4000
0!
0<
#6000
0"
1#
b1 %
0=
1R
1Q
#7000
1!
1<
b1 X
b1 Y
0T
0&
#8000
0!
0<
#10000
b11 %
1P
#11000
1!
1<
b10 X
b10 Y
#12000
0!
0<
#14000
b101 %
0P
1O
#15000
1!
1<
b11 X
b11 Y
#16000
0!
0<
#18000
1$
1S
#19000
1!
1<
b1 V
b100 X
b1 W
1;
0:
09
08
07
06
05
04
03
02
01
00
0/
0.
0-
0,
0+
0*
0)
0(
#20000
0!
0<
#22000
b1101 %
1N
#23000
1!
1<
b11 V
b101 X
b10 W
1:
